ranken/__init__.py
ranken/core.py
ranken/utils.py
ranken-0.0.3.dist-info/METADATA
ranken-0.0.3.dist-info/WHEEL
ranken-0.0.3.dist-info/top_level.txt
ranken-0.0.3.dist-info/RECORD
