Metadata-Version: 2.1
Name: ranken
Version: 0.0.3
Summary: Finding Entanglement Rank
Home-page: https://github.com/plutoniumm/ranken
Author: plutoniumm
License: MIT
Requires-Python: >=3.9
Requires-Dist: numpy
Requires-Dist: scipy
Provides-Extra: dev
Requires-Dist: pytest ; extra == 'dev'
Requires-Dist: twine ; extra == 'dev'
Requires-Dist: wheel ; extra == 'dev'
